MANIFEST.in
README.md
setup.cfg
setup.py
django_watchtower.egg-info/PKG-INFO
django_watchtower.egg-info/SOURCES.txt
django_watchtower.egg-info/dependency_links.txt
django_watchtower.egg-info/not-zip-safe
django_watchtower.egg-info/requires.txt
django_watchtower.egg-info/top_level.txt
watchtower/__init__.py
watchtower/admin.py
watchtower/apps.py
watchtower/conf.py
watchtower/middleware.py
watchtower/models.py
watchtower/router.py
watchtower/serializer.py
watchtower/tests.py
watchtower/db/__init__.py
watchtower/db/__pycache__/__init__.cpython-35.pyc
watchtower/db/__pycache__/__init__.cpython-36.pyc
watchtower/db/influx/__init__.py
watchtower/db/influx/__pycache__/__init__.cpython-35.pyc
watchtower/db/influx/__pycache__/__init__.cpython-36.pyc
watchtower/db/orm/__init__.py
watchtower/db/orm/__pycache__/__init__.cpython-35.pyc
watchtower/db/orm/__pycache__/__init__.cpython-36.pyc
watchtower/db/redis/__init__.py
watchtower/db/redis/__pycache__/__init__.cpython-35.pyc
watchtower/db/redis/__pycache__/__init__.cpython-36.pyc
watchtower/management/__init__.py
watchtower/management/conf.py
watchtower/management/__pycache__/__init__.cpython-35.pyc
watchtower/management/__pycache__/__init__.cpython-36.pyc
watchtower/management/commands/__init__.py
watchtower/management/commands/collect.py
watchtower/management/commands/__pycache__/__init__.cpython-35.pyc
watchtower/management/commands/__pycache__/__init__.cpython-36.pyc
watchtower/management/commands/__pycache__/autoreload.cpython-35.pyc
watchtower/management/commands/__pycache__/collect.cpython-35.pyc
watchtower/management/commands/__pycache__/collect.cpython-36.pyc
watchtower/management/commands/__pycache__/create_homepage.cpython-35.pyc
watchtower/management/commands/__pycache__/create_page.cpython-35.pyc
watchtower/migrations/0001_initial.py
watchtower/migrations/__init__.py
watchtower/migrations/__pycache__/0001_initial.cpython-35.pyc
watchtower/migrations/__pycache__/0001_initial.cpython-36.pyc
watchtower/migrations/__pycache__/__init__.cpython-35.pyc
watchtower/migrations/__pycache__/__init__.cpython-36.pyc