Metadata-Version: 1.1
Name: django-watchtower
Version: 0.2
Summary: Collect metrics and events from Django
Home-page: https://github.com/synw/django-watchtower
Author: synw
Author-email: synwe@yahoo.com
License: UNKNOWN
Download-URL: https://github.com/synw/django-watchtower/releases/tag/0.2
Keywords: django,monitoring
Platform: UNKNOWN
Classifier: Development Status :: 3 - Alpha
Classifier: Framework :: Django :: 1.11
Classifier: Intended Audience :: Developers
Classifier: License :: OSI Approved :: MIT License
Classifier: Programming Language :: Python :: 3.6
